viturka_nn/__init__.py
viturka_nn/client.py
viturka_nn/objectdetection.py
viturka_nn-0.1.40.dist-info/LICENSE
viturka_nn-0.1.40.dist-info/METADATA
viturka_nn-0.1.40.dist-info/WHEEL
viturka_nn-0.1.40.dist-info/top_level.txt
viturka_nn-0.1.40.dist-info/RECORD
