Metadata-Version: 2.1
Name: viturka-nn
Version: 0.1.40
Summary: A client library for deep federated learning platform.
License: MIT
Classifier: Programming Language :: Python :: 3
Classifier: License :: OSI Approved :: MIT License
Classifier: Operating System :: OS Independent
Requires-Python: >=3.6
License-File: LICENSE
Requires-Dist: numpy
Requires-Dist: pandas
Requires-Dist: torch
Requires-Dist: torchvision
Requires-Dist: torchmetrics (>=0.11.0)
Requires-Dist: pycocotools
Requires-Dist: scikit-learn
